dbaae/__init__.py
dbaae/__main__.py
dbaae/run_dbaae.py
dbaae/utils/__init__.py
dbaae/utils/dynamic.py
dbaae/utils/io.py
dbaae/utils/layers.py
dbaae/utils/train.py
dbaae-0.0.6.dist-info/METADATA
dbaae-0.0.6.dist-info/WHEEL
dbaae-0.0.6.dist-info/entry_points.txt
dbaae-0.0.6.dist-info/top_level.txt
dbaae-0.0.6.dist-info/RECORD
